<annotation>
	<folder>my-project-name</folder>
	<filename>Rock_Wren_0037_189256.jpg</filename>
	<path>/my-project-name/Rock_Wren_0037_189256.jpg</path>
	<source>
		<database>Unspecified</database>
	</source>
	<size>
		<width>500</width>
		<height>333</height>
		<depth>3</depth>
	</size>
	<object>
		<name>Resting</name>
		<pose>Unspecified</pose>
		<truncated>0</truncated>
		<difficult>0</difficult>
		<bndbox>
			<xmin>128</xmin>
			<ymin>65</ymin>
			<xmax>465</xmax>
			<ymax>324</ymax>
		</bndbox>
	</object>
</annotation>