<annotation>
	<folder>my-project-name</folder>
	<filename>Scarlet_Tanager_0012_138410.jpg</filename>
	<path>/my-project-name/Scarlet_Tanager_0012_138410.jpg</path>
	<source>
		<database>Unspecified</database>
	</source>
	<size>
		<width>500</width>
		<height>247</height>
		<depth>3</depth>
	</size>
	<object>
		<name>Resting</name>
		<pose>Unspecified</pose>
		<truncated>0</truncated>
		<difficult>0</difficult>
		<bndbox>
			<xmin>191</xmin>
			<ymin>12</ymin>
			<xmax>327</xmax>
			<ymax>231</ymax>
		</bndbox>
	</object>
</annotation>